tree_sitter_pgn-1.4.3.dist-info/RECORD
tree_sitter_pgn-1.4.3.dist-info/WHEEL
tree_sitter_pgn-1.4.3.dist-info/top_level.txt
tree_sitter_pgn-1.4.3.dist-info/METADATA
tree_sitter_pgn/__init__.pyi
tree_sitter_pgn/binding.c
tree_sitter_pgn/__init__.py
tree_sitter_pgn/py.typed
tree_sitter_pgn/_binding.abi3.so
tree_sitter_pgn/queries/highlights.scm
