Metadata-Version: 2.4
Name: tree-sitter-pgn
Version: 1.4.3
Summary: PGN grammar for tree-sitter
License: BSD-2-Clause
Project-URL: Homepage, https://github.com/rolandwalker/tree-sitter-pgn
Keywords: incremental,parsing,tree-sitter,PGN,chess
Classifier: Intended Audience :: Developers
Classifier: Topic :: Software Development :: Compilers
Classifier: Topic :: Text Processing :: Linguistic
Classifier: Typing :: Typed
Requires-Python: >=3.10
Provides-Extra: core
Requires-Dist: tree-sitter~=0.25.0; extra == "core"
